{
    "streamdeck_ui_version": 1,
    "state": {
        "AL25J2C06325": {
            "buttons": {
                "0": {
                    "0": {
                        "write": "",
                        "icon": "/home/jamesmaynard/Pictures/StreamDeck Icons/Standard-Clarity-Icons/Normal/App-Generic.png",
                        "command": "",
                        "text": "",
                        "switch_page": 2,
                        "keys": ""
                    },
                    "1": {
                        "write": "",
                        "switch_page": 3,
                        "command": "",
                        "icon": "/home/jamesmaynard/Pictures/StreamDeck Icons/Standard-Clarity-Icons/Normal/Misc-Websites.png"
                    },
                    "2": {
                        "write": "",
                        "switch_page": 10,
                        "icon": "/home/jamesmaynard/Pictures/StreamDeck Icons/Standard-Clarity-Icons/Normal/App-Spotify.png"
                    },
                    "3": {
                        "write": "",
                        "switch_page": 0
                    },
                    "4": {
                        "write": ""
                    },
                    "5": {},
                    "6": {
                        "write": "",
                        "text": "",
                        "switch_page": 10
                    },
                    "7": {
                        "write": "",
                        "switch_page": 0
                    },
                    "8": {
                        "write": "",
                        "switch_page": 0
                    },
                    "9": {
                        "write": "",
                        "switch_page": 0
                    },
                    "10": {},
                    "11": {},
                    "12": {},
                    "13": {},
                    "14": {}
                },
                "1": {
                    "0": {
                        "write": "",
                        "switch_page": 1,
                        "icon": "/home/jamesmaynard/Pictures/StreamDeck Icons/Standard-Clarity-Icons/Normal/Flashback.png",
                        "command": "",
                        "text": ""
                    },
                    "1": {
                        "write": "",
                        "text": "",
                        "command": "slack",
                        "icon": "/home/jamesmaynard/Pictures/StreamDeck Icons/Standard-Clarity-Icons/Normal/App-slack.png",
                        "switch_page": 1
                    },
                    "2": {
                        "write": "",
                        "text": "",
                        "icon": "/home/jamesmaynard/Pictures/StreamDeck Icons/Standard-Clarity-Icons/Normal/App-Discord.png",
                        "command": "discord",
                        "switch_page": 1
                    },
                    "3": {
                        "write": "",
                        "text": "",
                        "icon": "/home/jamesmaynard/Pictures/StreamDeck Icons/Standard-Clarity-Icons/Normal/App-Signal.png",
                        "command": "signal-desktop",
                        "switch_page": 1
                    },
                    "4": {
                        "write": "",
                        "text": "",
                        "icon": "/home/jamesmaynard/Pictures/StreamDeck Icons/Standard-Clarity-Icons/Normal/App-Spotify.png",
                        "command": "spotify  --force-device-scale-factor=1.75",
                        "switch_page": 1
                    },
                    "5": {
                        "write": "",
                        "text": "",
                        "icon": "/home/jamesmaynard/Pictures/StreamDeck Icons/Standard-Clarity-Icons/Normal/App-Terminal.png",
                        "command": "konsole",
                        "switch_page": 1
                    },
                    "6": {
                        "write": "",
                        "text": "",
                        "icon": "/home/jamesmaynard/Pictures/StreamDeck Icons/Standard-Clarity-Icons/Normal/App-Code.png",
                        "command": "code",
                        "switch_page": 1
                    },
                    "7": {
                        "write": "",
                        "text": "",
                        "command": "xdg-open https://google.com",
                        "icon": "/home/jamesmaynard/Pictures/StreamDeck Icons/Standard-Clarity-Icons/Normal/App-Chrome.png",
                        "switch_page": 1
                    },
                    "8": {
                        "write": "",
                        "text": "",
                        "command": "1password",
                        "icon": "/home/jamesmaynard/Pictures/StreamDeck Icons/Standard-Clarity-Icons/Normal/App-1password.png",
                        "switch_page": 1
                    },
                    "9": {
                        "write": "",
                        "text": "",
                        "switch_page": 1,
                        "icon": "/home/jamesmaynard/Pictures/StreamDeck Icons/Standard-Clarity-Icons/Normal/App-OBS.png",
                        "command": "obs"
                    },
                    "10": {
                        "write": "",
                        "text": "",
                        "switch_page": 1,
                        "command": "kmail",
                        "icon": "/home/jamesmaynard/Pictures/StreamDeck Icons/Standard-Clarity-Icons/Normal/App-Email.png"
                    },
                    "11": {
                        "write": "",
                        "text": "",
                        "command": "idea",
                        "icon": "/home/jamesmaynard/Pictures/StreamDeck Icons/Standard-Clarity-Icons/Normal/App-Intelij.png",
                        "switch_page": 1
                    },
                    "12": {
                        "write": "",
                        "text": "",
                        "command": "journey",
                        "switch_page": 1,
                        "keys": "",
                        "icon": "/home/jamesmaynard/Pictures/StreamDeck Icons/Standard-Clarity-Icons/Normal/App-Journey.png"
                    },
                    "13": {
                        "write": "",
                        "text": "",
                        "switch_page": 1,
                        "command": "kcalc",
                        "icon": "/home/jamesmaynard/Pictures/StreamDeck Icons/Standard-Clarity-Icons/Normal/App-Calculator.png"
                    },
                    "14": {
                        "command": "libreoffice",
                        "write": "",
                        "text": "",
                        "switch_page": 1,
                        "icon": "/home/jamesmaynard/Pictures/StreamDeck Icons/Standard-Clarity-Icons/Normal/App-Libreoffice.png"
                    }
                },
                "2": {
                    "0": {
                        "command": "",
                        "write": "",
                        "switch_page": 1,
                        "icon": "/home/jamesmaynard/Pictures/StreamDeck Icons/Standard-Clarity-Icons/Normal/Flashback.png"
                    },
                    "1": {
                        "command": "xdg-open https://www.google.com",
                        "write": "",
                        "switch_page": 1,
                        "icon": "/home/jamesmaynard/Pictures/StreamDeck Icons/Standard-Clarity-Icons/Normal/App-Google.png"
                    },
                    "2": {
                        "write": "",
                        "switch_page": 1,
                        "icon": "/home/jamesmaynard/Pictures/StreamDeck Icons/Standard-Clarity-Icons/Normal/Website-Gmail.png",
                        "command": "xdg-open https://mail.google.com"
                    },
                    "3": {
                        "command": "xdg-open https://calendar.google.com",
                        "write": "",
                        "switch_page": 1,
                        "icon": "/home/jamesmaynard/Pictures/StreamDeck Icons/Standard-Clarity-Icons/Normal/Website-Google-Calendar.png"
                    },
                    "4": {
                        "write": "",
                        "command": "xdg-open https://github.com",
                        "icon": "/home/jamesmaynard/Pictures/StreamDeck Icons/Standard-Clarity-Icons/Normal/Website-Github.png",
                        "switch_page": 0
                    },
                    "5": {
                        "write": "",
                        "command": "xdg-open https://news.bbc.co.uk",
                        "icon": "/home/jamesmaynard/Pictures/StreamDeck Icons/Standard-Clarity-Icons/Normal/Website-BBCNews.png",
                        "switch_page": 1
                    },
                    "6": {
                        "write": "",
                        "command": "xdg-open https://theregister.co.uk",
                        "icon": "/home/jamesmaynard/Pictures/StreamDeck Icons/Standard-Clarity-Icons/Normal/Website-TheRegister.png",
                        "keys": "",
                        "switch_page": 1
                    },
                    "7": {
                        "write": "",
                        "switch_page": 1,
                        "command": "xdg-open https://www.omgubuntu.co.uk",
                        "icon": "/home/jamesmaynard/Pictures/StreamDeck Icons/Standard-Clarity-Icons/Normal/Website-OMGUbuntu.png",
                        "keys": ""
                    },
                    "8": {
                        "command": "xdg-open https://fetlife.com",
                        "write": "",
                        "switch_page": 1,
                        "icon": "/home/jamesmaynard/Pictures/StreamDeck Icons/Standard-Clarity-Icons/Normal/Website-Fetlife.png"
                    },
                    "9": {
                        "command": "xdg-open https://www.recon.com",
                        "write": "",
                        "switch_page": 1,
                        "icon": "/home/jamesmaynard/Pictures/StreamDeck Icons/Standard-Clarity-Icons/Normal/Website-Recon.png"
                    },
                    "10": {
                        "command": "",
                        "write": "",
                        "switch_page": 0
                    },
                    "11": {},
                    "12": {},
                    "13": {},
                    "14": {}
                },
                "3": {
                    "0": {
                        "write": "",
                        "switch_page": 0
                    },
                    "1": {},
                    "2": {},
                    "3": {},
                    "4": {},
                    "5": {},
                    "6": {},
                    "7": {},
                    "8": {},
                    "9": {},
                    "10": {},
                    "11": {},
                    "12": {},
                    "13": {},
                    "14": {}
                },
                "4": {
                    "0": {
                        "write": ""
                    },
                    "1": {},
                    "2": {},
                    "3": {},
                    "4": {},
                    "5": {},
                    "6": {},
                    "7": {},
                    "8": {},
                    "9": {},
                    "10": {},
                    "11": {},
                    "12": {},
                    "13": {},
                    "14": {}
                },
                "5": {
                    "0": {
                        "write": ""
                    },
                    "1": {},
                    "2": {},
                    "3": {},
                    "4": {},
                    "5": {},
                    "6": {},
                    "7": {},
                    "8": {},
                    "9": {},
                    "10": {},
                    "11": {},
                    "12": {},
                    "13": {},
                    "14": {}
                },
                "6": {
                    "0": {
                        "write": ""
                    },
                    "1": {},
                    "2": {},
                    "3": {},
                    "4": {},
                    "5": {},
                    "6": {},
                    "7": {},
                    "8": {},
                    "9": {},
                    "10": {},
                    "11": {},
                    "12": {},
                    "13": {},
                    "14": {}
                },
                "7": {
                    "0": {
                        "write": ""
                    },
                    "1": {},
                    "2": {},
                    "3": {},
                    "4": {},
                    "5": {},
                    "6": {},
                    "7": {},
                    "8": {},
                    "9": {},
                    "10": {},
                    "11": {},
                    "12": {},
                    "13": {},
                    "14": {}
                },
                "8": {
                    "0": {
                        "write": "",
                        "text": "",
                        "keys": "",
                        "command": "",
                        "icon": "/home/jamesmaynard/Pictures/StreamDeck Icons/Standard-Clarity-Icons/Normal/Flashback.png",
                        "switch_page": 1
                    },
                    "1": {
                        "keys": "1",
                        "write": "",
                        "text": "1"
                    },
                    "2": {
                        "keys": "2",
                        "write": "",
                        "text": "2"
                    },
                    "3": {
                        "keys": "3",
                        "write": "",
                        "text": "3"
                    },
                    "4": {},
                    "5": {
                        "keys": "",
                        "write": "",
                        "text": "",
                        "switch_page": 0
                    },
                    "6": {
                        "keys": "4",
                        "write": "",
                        "text": "4"
                    },
                    "7": {
                        "keys": "5",
                        "write": "",
                        "text": "5"
                    },
                    "8": {
                        "keys": "6",
                        "write": "",
                        "text": "6"
                    },
                    "9": {},
                    "10": {},
                    "11": {
                        "keys": "7",
                        "write": "",
                        "text": "7"
                    },
                    "12": {
                        "keys": "8",
                        "write": "",
                        "text": "8",
                        "command": ""
                    },
                    "13": {
                        "keys": "9",
                        "write": "",
                        "text": "9"
                    },
                    "14": {}
                },
                "9": {
                    "0": {
                        "write": "",
                        "switch_page": 1,
                        "text": "",
                        "keys": "",
                        "icon": "/home/jamesmaynard/Pictures/StreamDeck Icons/Standard-Clarity-Icons/Normal/Flashback.png",
                        "command": ""
                    },
                    "1": {
                        "write": "",
                        "switch_page": 0,
                        "icon": "/home/jamesmaynard/Pictures/StreamDeck Icons/Standard-Clarity-Icons/Normal/App-Spotify.png",
                        "command": "spotify  --force-device-scale-factor=1.75"
                    },
                    "2": {
                        "command": "",
                        "write": ""
                    },
                    "3": {
                        "keys": "",
                        "write": ""
                    },
                    "4": {
                        "write": "",
                        "switch_page": 0,
                        "keys": "ctrl+alt+shift+F9",
                        "icon": "/home/jamesmaynard/Pictures/StreamDeck Icons/Standard-Clarity-Icons/Normal/Multimedia-Volume-Up.png"
                    },
                    "5": {},
                    "6": {
                        "write": "",
                        "keys": "ctrl+alt+shift+F5",
                        "command": "",
                        "icon": "/home/jamesmaynard/Pictures/StreamDeck Icons/Standard-Clarity-Icons/Normal/Multimedia-Previous.png",
                        "switch_page": 0
                    },
                    "7": {
                        "write": "",
                        "keys": "ctrl+alt+shift+F6",
                        "icon": "/home/jamesmaynard/Pictures/StreamDeck Icons/Standard-Clarity-Icons/Normal/Multimedia-Play+Pause.png",
                        "switch_page": 0
                    },
                    "8": {
                        "keys": "ctrl+alt+shift+F7",
                        "write": "",
                        "switch_page": 0,
                        "icon": "/home/jamesmaynard/Pictures/StreamDeck Icons/Standard-Clarity-Icons/Normal/Multimedia-Next.png"
                    },
                    "9": {
                        "keys": "ctrl+alt+shift+F10",
                        "write": "",
                        "icon": "/home/jamesmaynard/Pictures/StreamDeck Icons/Standard-Clarity-Icons/Normal/Multimedia-Mute.png",
                        "command": ""
                    },
                    "10": {},
                    "11": {},
                    "12": {
                        "keys": "",
                        "write": ""
                    },
                    "13": {
                        "keys": "",
                        "write": ""
                    },
                    "14": {
                        "keys": "ctrl+alt+shift+F8",
                        "write": "",
                        "icon": "/home/jamesmaynard/Pictures/StreamDeck Icons/Standard-Clarity-Icons/Normal/Multimedia-Volume-Down.png"
                    }
                }
            },
            "brightness": 99,
            "page": 0
        }
    }
}